{
"type": "FeatureCollection",
"name": "tr3-dobiv-package — r3-dobiv-03-2025 — 10GTL",
"crs": { "type": "name", "properties": { "name": "urn:ogc:def:crs:OGC:1.3:CRS84" } },
"features": [
{ "type": "Feature", "properties": { "fid": 1, "id": null, "Name": null, "description": null, "timestamp": null, "begin": null, "end": null, "altitudeMode": "clampToGround", "tessellate": -1, "extrude": 0, "visibility": -1, "drawOrder": null, "icon": null }, "geometry": { "type": "Point", "coordinates": [ 26.046763693900001, 42.196714937899998, 0.0 ] } }
]
}
